{
  "Routes": [
    {
      "DownstreamPathTemplate": "/api/products/{id}/reviews",
      "DownstreamScheme": "http",
      "DownstreamHostAndPorts": [
        {
          "Host": "localhost",
          "Port": "60001"
        }
      ],
      "UpstreamPathTemplate": "/api/products/{id}/reviews",
      "UpstreamHttpMethod": [ "GET" ]
    },
    {
      "DownstreamPathTemplate": "/api/reviews/{id}",
      "DownstreamScheme": "http",
      "DownstreamHostAndPorts": [
        {
          "Host": "localhost",
          "Port": "60001"
        }
      ],
      "UpstreamPathTemplate": "/api/reviews/{id}",
      "UpstreamHttpMethod": [ "GET" ]
    },
    {
      "DownstreamPathTemplate": "/api/products/{id}/reviews",
      "DownstreamScheme": "http",
      "DownstreamHostAndPorts": [
        {
          "Host": "localhost",
          "Port": "60001"
        }
      ],
      "UpstreamPathTemplate": "/api/products/{id}/reviews",
      "UpstreamHttpMethod": [ "POST" ]
    },
    {
      "DownstreamPathTemplate": "/api/products",
      "DownstreamScheme": "http",
      "DownstreamHostAndPorts": [
        {
          "Host": "localhost",
          "Port": "60000"
        }
      ],
      "UpstreamPathTemplate": "/api/products",
      "UpstreamHttpMethod": [ "GET" ]
    },
    {
      "DownstreamPathTemplate": "/api/products/{id}",
      "DownstreamScheme": "http",
      "DownstreamHostAndPorts": [
        {
          "Host": "localhost",
          "Port": "60000"
        }
      ],
      "UpstreamPathTemplate": "/api/products/{id}",
      "UpstreamHttpMethod": [ "GET" ]
    }
  ],
  "GlobalConfiguration": {
    "BaseUrl": "https://localhost:62012/"
  }
}